Metadata-Version: 1.0
Name: sspyrs
Version: 0.1a4
Summary: Lightweight interface for SSRS reports to python
Home-page: https://pypi.python.org/pypi/sspyrs
Author: James Nix
Author-email: james@nixanalytics.com
License: MIT
Keywords: ssrs report reporting sql
Platform: UNKNOWN
